curl_parser/__init__.py
curl_parser/cli.py
curl_parser/parser.py
easy_curl_parser-0.1.0.dist-info/licenses/LICENSE
easy_curl_parser-0.1.0.dist-info/METADATA
easy_curl_parser-0.1.0.dist-info/WHEEL
easy_curl_parser-0.1.0.dist-info/entry_points.txt
easy_curl_parser-0.1.0.dist-info/top_level.txt
easy_curl_parser-0.1.0.dist-info/RECORD
