Metadata-Version: 2.4
Name: easy-curl-parser
Version: 0.1.0
Summary: 一个用于解析cURL命令的Python库
Author-email: RosApr <287134285@qq.com>
License: MIT
Project-URL: Homepage, https://github.com/RosApr/curl-parser
Project-URL: Bug Reports, https://github.com/RosApr/curl-parser/issues
Project-URL: Source, https://github.com/RosApr/curl-parser
Keywords: curl,parser,http,request
Classifier: Development Status :: 3 - Alpha
Classifier: Intended Audience :: Developers
Classifier: Intended Audience :: End Users/Desktop
Classifier: License :: OSI Approved :: MIT License
Classifier: Programming Language :: Python :: 3
Classifier: Programming Language :: Python :: 3.7
Classifier: Programming Language :: Python :: 3.8
Classifier: Programming Language :: Python :: 3.9
Classifier: Programming Language :: Python :: 3.10
Classifier: Programming Language :: Python :: 3.11
Classifier: Topic :: Internet :: WWW/HTTP
Classifier: Topic :: Software Development :: Libraries :: Python Modules
Classifier: Topic :: System :: Networking
Classifier: Topic :: Utilities
Classifier: Topic :: Text Processing :: Markup
Classifier: Topic :: System :: Systems Administration
Requires-Python: >=3.7
License-File: LICENSE
Provides-Extra: dev
Dynamic: license-file
